[{"fields": {"username": "AlejandroVeintimilla", "first_name": "Alejandro", "last_name": "Veintimilla", "is_active": true, "is_superuser": false, "is_staff": false, "last_login": "2015-09-22T19:27:44.577Z", "groups": [], "user_permissions": [], "password": "!W2iN9GD5IA7vebjHIwotwSkhDPBreMeSJSsDJFEn", "email": "alejoveintimilla@gmail.com", "date_joined": "2015-05-21T00:40:45.140Z"}, "model": "auth.user", "pk": 1}, {"fields": {"username": "alejoveintimilla", "first_name": "Alejandro", "last_name": "Veintimilla", "is_active": true, "is_superuser": false, "is_staff": false, "last_login": "2015-06-18T17:11:24.468Z", "groups": [], "user_permissions": [], "password": "!eqhmB9eaMlKxV8mOCy9I7tev512pwlrgjk0kimfP", "email": "alejoveintimilla@gmail.com", "date_joined": "2015-05-21T01:44:41.798Z"}, "model": "auth.user", "pk": 2}, {"fields": {"username": "MoshMoosh", "first_name": "Mosh", "last_name": "Moosh", "is_active": true, "is_superuser": false, "is_staff": false, "last_login": "2015-05-22T18:37:21.242Z", "groups": [], "user_permissions": [], "password": "!ofVRtUJXMFb41vFYjgEUKw9FqRbgx1wayOA52i8k", "email": "", "date_joined": "2015-05-22T18:37:21.118Z"}, "model": "auth.user", "pk": 3}, {"fields": {"username": "admin", "first_name": "", "last_name": "", "is_active": true, "is_superuser": true, "is_staff": true, "last_login": "2015-12-02T17:36:27.564Z", "groups": [], "user_permissions": [], "password": "pbkdf2_sha256$20000$5CywRtnJnTrz$whck4IVybE60w0KnOyP27PuD/DYKZbl10YsUdaTtALg=", "email": "admin@gmail.com", "date_joined": "2015-05-22T19:23:07Z"}, "model": "auth.user", "pk": 4}, {"fields": {"username": "stef.doorman", "first_name": "Stefany", "last_name": "Doorman Flores", "is_active": true, "is_superuser": false, "is_staff": false, "last_login": "2015-05-27T00:07:51.937Z", "groups": [], "user_permissions": [], "password": "!9vYMccBef1EhJr9PYhxS8eGPfHcYZlIaDyl6tF3h", "email": "stef.doorman@gmail.com", "date_joined": "2015-05-26T04:47:27.486Z"}, "model": "auth.user", "pk": 5}, {"fields": {"username": "PaulNarvaez", "first_name": "Paul", "last_name": "Narvaez", "is_active": true, "is_superuser": false, "is_staff": false, "last_login": "2015-06-22T19:53:47.839Z", "groups": [], "user_permissions": [], "password": "!etnqwpccQHtySZaiWrzZQmTw3Ipmqo10ro3pofUK", "email": "paulnrvz@live.com", "date_joined": "2015-05-26T17:24:30.289Z"}, "model": "auth.user", "pk": 6}, {"fields": {"username": "paulnrvz", "first_name": "Paul", "last_name": "Narvaez", "is_active": true, "is_superuser": false, "is_staff": false, "last_login": "2015-05-26T17:36:27.295Z", "groups": [], "user_permissions": [], "password": "!wIZ1S4Tcig6bO3RPetRS9Lr4FiLxEHmzJTevnpYC", "email": "paulnrvz@gmail.com", "date_joined": "2015-05-26T17:36:26.973Z"}, "model": "auth.user", "pk": 7}, {"fields": {"username": "jativafrancisco", "first_name": "francisco", "last_name": "jativa", "is_active": true, "is_superuser": false, "is_staff": false, "last_login": "2015-05-26T18:28:27.041Z", "groups": [], "user_permissions": [], "password": "!BMGkVYlJAgTvYZ6XC9bzqnIDgIIwkvdMnB9XzpPX", "email": "jativafrancisco@gmail.com", "date_joined": "2015-05-26T18:28:26.928Z"}, "model": "auth.user", "pk": 8}, {"fields": {"username": "AlfonsoCelleri", "first_name": "Alfonso", "last_name": "Celleri", "is_active": true, "is_superuser": false, "is_staff": false, "last_login": "2015-05-26T18:48:11.806Z", "groups": [], "user_permissions": [], "password": "!94DW6shWh6TxNsvj0hCqC1yLIZo40XHq5Ywxf5wB", "email": "alfonsocelleri@hotmail.com", "date_joined": "2015-05-26T18:48:11.741Z"}, "model": "auth.user", "pk": 9}, {"fields": {"username": "Santiago", "first_name": "Santiago", "last_name": "Veintimilla", "is_active": true, "is_superuser": false, "is_staff": false, "last_login": "2015-06-02T22:34:29Z", "groups": [], "user_permissions": [], "password": "!o9kNDzQpP5gAi0QeyI9TvhXrSIGRyHcWV9C2WwjB", "email": "santiagoveintimilla@gmail.com", "date_joined": "2015-05-27T23:58:39Z"}, "model": "auth.user", "pk": 10}, {"fields": {"username": "DanielVeintimilla", "first_name": "Daniel", "last_name": "Veintimilla", "is_active": true, "is_superuser": false, "is_staff": false, "last_login": "2015-06-06T18:03:42.996Z", "groups": [], "user_permissions": [], "password": "!3eDs7p18jHP7dmo8VuPdQLrjYccwOZSnpDUzmBXe", "email": "danielveinti@gmail.com", "date_joined": "2015-06-02T21:46:47.395Z"}, "model": "auth.user", "pk": 11}, {"fields": {"username": "CoiaEcuador", "first_name": "Coia", "last_name": "Ecuador", "is_active": true, "is_superuser": false, "is_staff": false, "last_login": "2015-06-17T23:15:59.851Z", "groups": [], "user_permissions": [], "password": "!YSXk811yRdeS1cy2I2gAweOO2UbN2TgmfAgeoYD3", "email": "coiaecuador@gmail.com", "date_joined": "2015-06-02T22:31:39.863Z"}, "model": "auth.user", "pk": 12}, {"fields": {"username": "bnalohim", "first_name": "Sebastian", "last_name": "Veintimilla", "is_active": true, "is_superuser": false, "is_staff": false, "last_login": "2015-07-29T00:42:15.766Z", "groups": [], "user_permissions": [], "password": "!jNEi5z8HUCaqPMRYf0i7oqJp1pLEzD9NtSGvcG55", "email": "bnalohim@gmail.com", "date_joined": "2015-06-08T22:52:30.211Z"}, "model": "auth.user", "pk": 13}, {"fields": {"username": "MarioCeli", "first_name": "Mario", "last_name": "Celi", "is_active": true, "is_superuser": false, "is_staff": false, "last_login": "2015-07-19T17:01:18.222Z", "groups": [], "user_permissions": [], "password": "!JV1ReMhDYJkOdJsVm6MDmfGmEofM2vh4SKTYFG9X", "email": "mcelicalderon@gmail.com", "date_joined": "2015-06-08T23:11:20.196Z"}, "model": "auth.user", "pk": 14}, {"fields": {"username": "StefanyDoorman", "first_name": "Stefany", "last_name": "Doorman", "is_active": true, "is_superuser": false, "is_staff": false, "last_login": "2015-07-12T23:51:38.626Z", "groups": [], "user_permissions": [], "password": "!czGb32ILtp11LWoT7ICC94GLFSD9jYq1u8QulMON", "email": "stef.doorman@gmail.com", "date_joined": "2015-06-09T00:02:17.988Z"}, "model": "auth.user", "pk": 15}, {"fields": {"username": "dairon.medina", "first_name": "Dairon", "last_name": "Medina Caro", "is_active": true, "is_superuser": false, "is_staff": false, "last_login": "2015-06-09T20:38:54.548Z", "groups": [], "user_permissions": [], "password": "!3J7R30jJSoSMvNcIfCCngsUQVIlTvNl5iVgBdi1A", "email": "dairon.medina@gmail.com", "date_joined": "2015-06-09T20:38:54.424Z"}, "model": "auth.user", "pk": 16}, {"fields": {"username": "solopunks803", "first_name": "Jorge", "last_name": "Sevilla", "is_active": true, "is_superuser": false, "is_staff": false, "last_login": "2015-06-10T02:50:53.555Z", "groups": [], "user_permissions": [], "password": "!YA1WKzqxOLpyPDPOtEANWQInohv8d84ZafXjUSdN", "email": "solopunks803@gmail.com", "date_joined": "2015-06-10T02:50:53.187Z"}, "model": "auth.user", "pk": 17}, {"fields": {"username": "usangiorgi", "first_name": "Ugo", "last_name": "Sangiorgi", "is_active": true, "is_superuser": false, "is_staff": false, "last_login": "2015-06-12T16:38:03.516Z", "groups": [], "user_permissions": [], "password": "!CoaV2GGujDc7HzyNXwREMRXHYu6z3eHTkF8rVWh1", "email": "usangiorgi@awa.ec", "date_joined": "2015-06-12T16:38:03.437Z"}, "model": "auth.user", "pk": 18}, {"fields": {"username": "andres.nietoarguello", "first_name": "Andres", "last_name": "Nieto Arguello", "is_active": true, "is_superuser": false, "is_staff": false, "last_login": "2015-07-16T12:03:36.430Z", "groups": [], "user_permissions": [], "password": "!rDnkJ0hX42QzrhDLuXCZHYcVXebDkBJgbFRbDA2Z", "email": "andres.nietoarguello@gmail.com", "date_joined": "2015-06-15T17:52:25.687Z"}, "model": "auth.user", "pk": 19}, {"fields": {"username": "CarlosA.DeSmedt", "first_name": "Carlos", "last_name": "De Smedt", "is_active": true, "is_superuser": false, "is_staff": false, "last_login": "2015-07-16T00:31:09.207Z", "groups": [], "user_permissions": [], "password": "!ReWKFNhON5SBflhkmJMXigFbHcJwYsvnJGfrk8Id", "email": "wikicarlos@gmail.com", "date_joined": "2015-06-17T07:59:14.735Z"}, "model": "auth.user", "pk": 20}, {"fields": {"username": "MiguelomAj\u00e1", "first_name": "Miguelom", "last_name": "Aj\u00e1", "is_active": true, "is_superuser": false, "is_staff": false, "last_login": "2015-06-17T15:55:49.475Z", "groups": [], "user_permissions": [], "password": "!xfvxqISwK3aHIm0p8TRm854hSNBZZS9QKU22vH9Z", "email": "miguelo.aja@gmail.com", "date_joined": "2015-06-17T15:55:49.403Z"}, "model": "auth.user", "pk": 21}, {"fields": {"username": "AgustinSebastianNovoaCarvaj", "first_name": "Agustin Sebastian", "last_name": "Novoa Carvajal", "is_active": true, "is_superuser": false, "is_staff": false, "last_login": "2015-06-18T05:04:56.628Z", "groups": [], "user_permissions": [], "password": "!rv8PsanaFtS5Gz6uIivy6kP4Gf7vV49nJNDlILMm", "email": "tinsebas_8@hotmail.com", "date_joined": "2015-06-18T05:04:56.541Z"}, "model": "auth.user", "pk": 22}, {"fields": {"username": "farseer", "first_name": "Sebas", "last_name": "V", "is_active": true, "is_superuser": true, "is_staff": true, "last_login": "2015-06-18T22:58:27.895Z", "groups": [], "user_permissions": [], "password": "pbkdf2_sha256$20000$DKJEPsWeFUy1$iJ+34rTz8oZsrMsDoTGdIYvi15ySsj133j43AFV8G+c=", "email": "sebas_v8@gmail.com", "date_joined": "2015-06-18T17:13:03Z"}, "model": "auth.user", "pk": 23}, {"fields": {"username": "IsabelleMacias", "first_name": "Isabelle", "last_name": "Macias", "is_active": true, "is_superuser": false, "is_staff": false, "last_login": "2015-06-21T23:28:53.845Z", "groups": [], "user_permissions": [], "password": "!C8ycWLCpmdh2PL8PNMsytTZB3nYEmvPLd7rFD2mS", "email": "isabelita15_31@hotmail.com", "date_joined": "2015-06-21T23:28:53.753Z"}, "model": "auth.user", "pk": 24}, {"fields": {"username": "danielaborjakaisin", "first_name": "Daniela", "last_name": "Borja Kaisin", "is_active": true, "is_superuser": false, "is_staff": false, "last_login": "2015-06-23T20:11:55.686Z", "groups": [], "user_permissions": [], "password": "!w4h5dQWwJfzDGcA9ZD4pIi7JQb5a9CbsRFqZXsdC", "email": "danielaborjakaisin@gmail.com", "date_joined": "2015-06-23T20:11:55.606Z"}, "model": "auth.user", "pk": 25}, {"fields": {"username": "pazgomez3008", "first_name": "paz", "last_name": "gomez", "is_active": true, "is_superuser": false, "is_staff": false, "last_login": "2015-07-28T01:29:49.073Z", "groups": [], "user_permissions": [], "password": "!YMSCKDbpuQwZ2W3DypPN93zm2jOpMudaPtxopJxW", "email": "pazgomez3008@gmail.com", "date_joined": "2015-06-23T21:19:03.368Z"}, "model": "auth.user", "pk": 26}, {"fields": {"username": "ivars31", "first_name": "Iv\u00e1n", "last_name": "R\u00edos", "is_active": true, "is_superuser": false, "is_staff": false, "last_login": "2015-06-24T15:54:12.860Z", "groups": [], "user_permissions": [], "password": "!ILk0QurfEYYbvXeYizRzDMGOteQ5NYCXHFuhDcWf", "email": "ivars31@gmail.com", "date_joined": "2015-06-24T15:54:12.791Z"}, "model": "auth.user", "pk": 27}, {"fields": {"username": "IsabelMena", "first_name": "Isabel", "last_name": "Mena", "is_active": true, "is_superuser": false, "is_staff": false, "last_login": "2015-06-24T16:06:15.635Z", "groups": [], "user_permissions": [], "password": "!RY6tb1kiKO7PFm784Q8cymHv2YBPhDN6E2G9qbEf", "email": "isabelmena2002@yahoo.com", "date_joined": "2015-06-24T16:06:15.483Z"}, "model": "auth.user", "pk": 28}, {"fields": {"username": "PedroAlmeidaHayek", "first_name": "Pedro", "last_name": "Hayek", "is_active": true, "is_superuser": false, "is_staff": false, "last_login": "2015-06-24T20:33:48.785Z", "groups": [], "user_permissions": [], "password": "!kVuevqLTmlbqtxcmw0NwaIp5cwP5HQJQpBG7khP3", "email": "pdro_ha@hotmail.com", "date_joined": "2015-06-24T20:33:48.695Z"}, "model": "auth.user", "pk": 29}, {"fields": {"username": "AndreaAlmeidaHayek", "first_name": "Andrea", "last_name": "Almeida Hayek", "is_active": true, "is_superuser": false, "is_staff": false, "last_login": "2015-06-25T01:07:39.169Z", "groups": [], "user_permissions": [], "password": "!Nuy8mu0pO1G3eQXSjielTzfhKvvFwynjdG7Vox4f", "email": "andrealmayek@hotmail.com", "date_joined": "2015-06-25T01:07:39.084Z"}, "model": "auth.user", "pk": 30}, {"fields": {"username": "Andr\u00e9sMu\u00f1oz", "first_name": "Andr\u00e9s", "last_name": "Mu\u00f1oz", "is_active": true, "is_superuser": false, "is_staff": false, "last_login": "2015-06-25T04:07:53.272Z", "groups": [], "user_permissions": [], "password": "!BzgjwMZTZHvH9g55z7mC2s3wcTxixo4l6dY2g9K7", "email": "asmz5488@gmail.com", "date_joined": "2015-06-25T04:07:53.204Z"}, "model": "auth.user", "pk": 31}, {"fields": {"username": "JorgeMorales", "first_name": "Jorge", "last_name": "Morales", "is_active": true, "is_superuser": false, "is_staff": false, "last_login": "2015-07-20T21:37:43.117Z", "groups": [], "user_permissions": [], "password": "!3AAajOPKKz6qNgbx7xowIsg4L8MvT9HTRUbMgoDE", "email": "levithan21@hotmail.com", "date_joined": "2015-06-29T22:39:10.059Z"}, "model": "auth.user", "pk": 32}, {"fields": {"username": "ccastaneda", "first_name": "Carlos", "last_name": "Casteneda", "is_active": true, "is_superuser": false, "is_staff": false, "last_login": "2015-07-08T22:48:19.379Z", "groups": [], "user_permissions": [], "password": "pbkdf2_sha256$20000$yvrHyxeEd4Dz$3iQ88eaUAMZFJq6DccHGccEcxU2jI94aXn47ABMGyc0=", "email": "alejoveintimilla@gmail.com", "date_joined": "2015-07-08T22:42:56Z"}, "model": "auth.user", "pk": 33}, {"fields": {"username": "Iv\u00e1nS\u00e1enz", "first_name": "Iv\u00e1n", "last_name": "S\u00e1enz", "is_active": true, "is_superuser": false, "is_staff": false, "last_login": "2015-07-09T01:41:54.408Z", "groups": [], "user_permissions": [], "password": "!hMTjqUZD3v0RG3rBYSA5rcPLjb0PFhUvAZA3iqmc", "email": "isaenz1981@hotmail.com", "date_joined": "2015-07-09T01:41:54.323Z"}, "model": "auth.user", "pk": 34}, {"fields": {"username": "DanielAlejandroBarrionuevoP", "first_name": "Daniel", "last_name": "Padilla", "is_active": true, "is_superuser": false, "is_staff": false, "last_login": "2015-07-12T02:07:25.690Z", "groups": [], "user_permissions": [], "password": "!WBBQndA9Ozvbax4Ku6EjEDsXazgg6iUvyGiRidg7", "email": "dabp74@hotmail.com", "date_joined": "2015-07-12T02:07:25.594Z"}, "model": "auth.user", "pk": 35}, {"fields": {"username": "MaryQuishpe", "first_name": "Mary", "last_name": "Quishpe", "is_active": true, "is_superuser": false, "is_staff": false, "last_login": "2015-07-13T16:59:17.141Z", "groups": [], "user_permissions": [], "password": "!KGHu4A3XfVHI41LLaK0JIHBOj2mv4KHisykfZb7r", "email": "maryblue4@yahoo.es", "date_joined": "2015-07-13T16:59:17.043Z"}, "model": "auth.user", "pk": 36}, {"fields": {"username": "FranciscoVivanco", "first_name": "Francisco", "last_name": "Vivanco", "is_active": true, "is_superuser": false, "is_staff": false, "last_login": "2015-07-14T18:19:21.776Z", "groups": [], "user_permissions": [], "password": "!4zqKXTANZAbmioNHyhvDwlvLss4ChRDeE0gBGQlQ", "email": "", "date_joined": "2015-07-14T18:19:21.683Z"}, "model": "auth.user", "pk": 37}, {"fields": {"username": "enelmundo", "first_name": "Ricardo", "last_name": "Arcos", "is_active": true, "is_superuser": false, "is_staff": false, "last_login": null, "groups": [], "user_permissions": [], "password": "pbkdf2_sha256$20000$nDvzvmOeNkds$NnSvNse6VcWycAZeu3cOopIILGTbtJhrocQw061ChNg=", "email": "thecriptoanarquist@gmail.com", "date_joined": "2015-07-15T17:08:14Z"}, "model": "auth.user", "pk": 38}, {"fields": {"username": "AnaCristinaGonz\u00e1lezCaraball", "first_name": "Ana", "last_name": "Gonz\u00e1lez Caraballoso", "is_active": true, "is_superuser": false, "is_staff": false, "last_login": "2015-07-17T00:23:49.004Z", "groups": [], "user_permissions": [], "password": "!H8VAAcJdzZeiyiVe3ahBbTnU6ynapCMvcPmvssoO", "email": "anacaraballoso@gmail.com", "date_joined": "2015-07-17T00:23:48.923Z"}, "model": "auth.user", "pk": 39}, {"fields": {"username": "BrianMolina", "first_name": "Brian", "last_name": "Molina", "is_active": true, "is_superuser": false, "is_staff": false, "last_login": "2015-07-18T20:21:03.289Z", "groups": [], "user_permissions": [], "password": "!ooJGGFnFSYyQ2cm5Op9FLOCdkF3j6RWTsU5dCuA4", "email": "b_m_10_27@hotmail.com", "date_joined": "2015-07-18T20:21:03.229Z"}, "model": "auth.user", "pk": 40}, {"fields": {"username": "LigiaCeciliaReyesCarrera", "first_name": "Ligia Cecilia", "last_name": "Reyes Carrera", "is_active": true, "is_superuser": false, "is_staff": false, "last_login": "2015-07-20T22:14:20.592Z", "groups": [], "user_permissions": [], "password": "!TASS3WZ7CjBAhsyP5SwZLiLHh3YpX3qyafLfWsWF", "email": "cecy_r02@yahoo.com", "date_joined": "2015-07-20T22:14:20.495Z"}, "model": "auth.user", "pk": 41}, {"fields": {"username": "MarciaIntriago", "first_name": "Marcia", "last_name": "Intriago", "is_active": true, "is_superuser": false, "is_staff": false, "last_login": "2015-07-21T18:47:18.117Z", "groups": [], "user_permissions": [], "password": "!Ppupbny5OzGoMslcCKwhQkRwwWLzuubVrweFYlzE", "email": "mbintriago@hotmail.com", "date_joined": "2015-07-21T18:47:17.925Z"}, "model": "auth.user", "pk": 42}, {"fields": {"username": "ChurosVallejo", "first_name": "Churos", "last_name": "Vallejo", "is_active": true, "is_superuser": false, "is_staff": false, "last_login": "2015-07-23T20:11:50.102Z", "groups": [], "user_permissions": [], "password": "!oooARGne1LwO7mBOC9cBOuyUaTuagGCowzJNYZHD", "email": "rober_vallejo@hotmail.com", "date_joined": "2015-07-23T20:11:50.009Z"}, "model": "auth.user", "pk": 43}, {"fields": {"username": "MariaugustaRojas", "first_name": "Mariaugusta", "last_name": "Rojas", "is_active": true, "is_superuser": false, "is_staff": false, "last_login": "2015-07-24T14:14:18.568Z", "groups": [], "user_permissions": [], "password": "!hDyyjwRE0G92V4zK92eqDyoqGyNnHssyblXkPnwb", "email": "magusrojas@gmail.com", "date_joined": "2015-07-24T14:14:18.400Z"}, "model": "auth.user", "pk": 44}, {"fields": {"username": "romeocardenase9", "first_name": "Romeo", "last_name": "C\u00e1rdenas", "is_active": true, "is_superuser": false, "is_staff": false, "last_login": "2015-07-24T22:57:40.409Z", "groups": [], "user_permissions": [], "password": "!g3dhWOlZVfgEn4fXQaoBZ3dbsPIXFqP03GbgHSTX", "email": "romeocardenase9@gmail.com", "date_joined": "2015-07-24T22:57:40.329Z"}, "model": "auth.user", "pk": 45}, {"fields": {"username": "JuanFernandoEnr\u00edquezBravo", "first_name": "Juan Fernando", "last_name": "Enr\u00edquez Bravo", "is_active": true, "is_superuser": false, "is_staff": false, "last_login": "2015-07-26T00:00:44.852Z", "groups": [], "user_permissions": [], "password": "!5XdTYfV8OTWo9chtkoGhHaO066vFo8YVAPVl29Ck", "email": "juanfer_eb99@hotmail.com", "date_joined": "2015-07-26T00:00:44.769Z"}, "model": "auth.user", "pk": 46}, {"fields": {"username": "AlissonEstefan\u00eda", "first_name": "Alisson", "last_name": "Estefan\u00eda", "is_active": true, "is_superuser": false, "is_staff": false, "last_login": "2015-07-26T00:17:15.998Z", "groups": [], "user_permissions": [], "password": "!hcgXStm19Qv71U127ZtmmBAioQwAZ09aU4vjivGD", "email": "alisson_13@hotmail.it", "date_joined": "2015-07-26T00:17:15.948Z"}, "model": "auth.user", "pk": 47}, {"fields": {"username": "PaulachaGatica", "first_name": "Paulacha", "last_name": "Gatica", "is_active": true, "is_superuser": false, "is_staff": false, "last_login": "2015-07-27T05:13:06.402Z", "groups": [], "user_permissions": [], "password": "!l7LtCE8tfCJT0YyFVJNcAt5472sDwKBp2tSYgsxN", "email": "paula.gatica@estud.usfq.edu.ec", "date_joined": "2015-07-27T05:13:06.329Z"}, "model": "auth.user", "pk": 48}, {"fields": {"username": "grupomendozast", "first_name": "Francisco", "last_name": "Mendoza", "is_active": true, "is_superuser": false, "is_staff": false, "last_login": "2015-07-28T17:00:30.774Z", "groups": [], "user_permissions": [], "password": "!gT5Wtv3yUxf7F0YgGsrp565j6azBNFT9BgenN2ux", "email": "grupomendozast@gmail.com", "date_joined": "2015-07-28T17:00:30.439Z"}, "model": "auth.user", "pk": 49}, {"fields": {"username": "AnnabellaValencia", "first_name": "Annabella", "last_name": "Valencia", "is_active": true, "is_superuser": false, "is_staff": false, "last_login": "2015-07-28T17:32:23.604Z", "groups": [], "user_permissions": [], "password": "!lSUtZ4RPHyc4LQV9aspE3fgfwdezjsgujLHTdE8K", "email": "annabella923@hotmail.com", "date_joined": "2015-07-28T17:32:23.458Z"}, "model": "auth.user", "pk": 50}, {"fields": {"username": "CynthiaGuerrero", "first_name": "Cynthia", "last_name": "Guerrero", "is_active": true, "is_superuser": false, "is_staff": false, "last_login": "2015-08-04T19:31:29.624Z", "groups": [], "user_permissions": [], "password": "!3n8XI6Ul1LT7A3IMPvp1N6kVXZLhTcLqC7GFcAhL", "email": "cdguerrerochk@hotmail.com", "date_joined": "2015-08-04T19:26:19.995Z"}, "model": "auth.user", "pk": 51}, {"fields": {"username": "DanielaGuerrero", "first_name": "Daniela", "last_name": "Guerrero", "is_active": true, "is_superuser": false, "is_staff": false, "last_login": "2015-08-04T20:42:37.885Z", "groups": [], "user_permissions": [], "password": "!7hqSjup8dhUeyIqIAssjq4JhNhcHpmyliekgYJ5B", "email": "daniguerc@hotmail.com", "date_joined": "2015-08-04T20:42:37.830Z"}, "model": "auth.user", "pk": 52}, {"fields": {"username": "MaferCarpio", "first_name": "Mafer", "last_name": "Carpio", "is_active": true, "is_superuser": false, "is_staff": false, "last_login": "2015-08-06T01:19:13.662Z", "groups": [], "user_permissions": [], "password": "!W3E4MGEwimI99xpjlyVZGwgTwmyw9TzgtmWLbOGW", "email": "maferc27@gmail.com", "date_joined": "2015-08-06T01:19:13.560Z"}, "model": "auth.user", "pk": 53}, {"fields": {"username": "TefaDonoso", "first_name": "Tefa", "last_name": "Donoso", "is_active": true, "is_superuser": false, "is_staff": false, "last_login": "2015-08-06T03:01:34.420Z", "groups": [], "user_permissions": [], "password": "!cHvMKHJQJUkkNLNksZqUFz9mCxU4PQMN3RcDmKZu", "email": "", "date_joined": "2015-08-06T03:01:34.361Z"}, "model": "auth.user", "pk": 54}, {"fields": {"username": "mishellstefany23", "first_name": "Mishell", "last_name": "Monar", "is_active": true, "is_superuser": false, "is_staff": false, "last_login": "2015-08-10T18:49:36.133Z", "groups": [], "user_permissions": [], "password": "!g9WKNkDK8Vf2hijvfHveqtLtdwIIwDCGVzPh4WW8", "email": "mishellstefany23@gmail.com", "date_joined": "2015-08-10T18:49:36.053Z"}, "model": "auth.user", "pk": 55}, {"fields": {"username": "KarolinaChamorro", "first_name": "Karolina", "last_name": "Chamorro", "is_active": true, "is_superuser": false, "is_staff": false, "last_login": "2015-08-12T14:38:14.448Z", "groups": [], "user_permissions": [], "password": "!xoB8qXbrsM0MGbNgID5IXJpLsCu2k234chxRSK7B", "email": "chiquita9008@hotmail.com", "date_joined": "2015-08-12T14:38:14.238Z"}, "model": "auth.user", "pk": 56}, {"fields": {"username": "KevinCuadradoSerrano", "first_name": "Kevin", "last_name": "Cuadrado Serrano", "is_active": true, "is_superuser": false, "is_staff": false, "last_login": "2015-08-16T02:54:10.523Z", "groups": [], "user_permissions": [], "password": "!n9qLvZ7lQh5W8Y3GwrnAM9JJdqhnnjOnB10AESuj", "email": "kevincuadrado69@yahoo.com", "date_joined": "2015-08-16T02:54:10.008Z"}, "model": "auth.user", "pk": 57}, {"fields": {"username": "KeniaMoreno", "first_name": "Kenia", "last_name": "Moreno", "is_active": true, "is_superuser": false, "is_staff": false, "last_login": "2015-08-17T02:00:50.872Z", "groups": [], "user_permissions": [], "password": "!wDp80ASHNkXroxVtvjQH39Lm5j08JMW2cIWkio82", "email": "kenia-31-m@hotmail.com", "date_joined": "2015-08-17T02:00:50.773Z"}, "model": "auth.user", "pk": 58}, {"fields": {"username": "Am\u00e9lieCarlene", "first_name": "Am\u00e9lie", "last_name": "Carlene", "is_active": true, "is_superuser": false, "is_staff": false, "last_login": "2015-08-17T16:39:52.951Z", "groups": [], "user_permissions": [], "password": "!eqrCk5daFKj4tdUSwyG4op4MYkOZavetZgge9P1R", "email": "karolina_aguirre@outlook.es", "date_joined": "2015-08-17T16:39:52.770Z"}, "model": "auth.user", "pk": 59}, {"fields": {"username": "StyvenCatucuamba", "first_name": "Styven", "last_name": "Catucuamba", "is_active": true, "is_superuser": false, "is_staff": false, "last_login": "2015-08-18T03:37:05.013Z", "groups": [], "user_permissions": [], "password": "!3bCJwjrfRnrCvqZwIe9oBNwmDiYnCHfYwYXI8WVo", "email": "styven.catu1218@hotmail.com", "date_joined": "2015-08-18T03:37:04.908Z"}, "model": "auth.user", "pk": 60}, {"fields": {"username": "pavitopakarina", "first_name": "Cristina", "last_name": "Acosta", "is_active": true, "is_superuser": false, "is_staff": false, "last_login": "2015-08-30T23:01:22.291Z", "groups": [], "user_permissions": [], "password": "!TFUYNOOrnmNWVYobpxAdO1yeciFPiUEIFBSyZ7a9", "email": "pavitopakarina@gmail.com", "date_joined": "2015-08-30T23:01:22.128Z"}, "model": "auth.user", "pk": 61}, {"fields": {"username": "GustavoEndara", "first_name": "Gustavo", "last_name": "Endara", "is_active": true, "is_superuser": false, "is_staff": false, "last_login": "2015-09-21T02:26:52.860Z", "groups": [], "user_permissions": [], "password": "!7OMaFH0zYwBcXj9afjSkol8WwkKACH2ze4eE8b4q", "email": "gux@rocketmail.com", "date_joined": "2015-09-21T02:26:52.723Z"}, "model": "auth.user", "pk": 62}, {"fields": {"username": "DaironMedina", "first_name": "Dairon", "last_name": "Medina", "is_active": true, "is_superuser": false, "is_staff": false, "last_login": "2015-09-29T17:52:37.062Z", "groups": [], "user_permissions": [], "password": "!hbLQ17c3kK44IeOSlGSAlK5370J1T0FFsoolD4qw", "email": "dairon.medina@gmail.com", "date_joined": "2015-09-29T17:52:36.946Z"}, "model": "auth.user", "pk": 63}, {"fields": {"username": "NataliaCartolini", "first_name": "Natalia", "last_name": "Cartolini", "is_active": true, "is_superuser": false, "is_staff": false, "last_login": "2015-10-07T17:04:42.834Z", "groups": [], "user_permissions": [], "password": "!e0gtFzyRe9mkiQNcMeuY37V0SNI20tC3VekW5LnC", "email": "lobitadelsur@gmail.com", "date_joined": "2015-10-07T17:04:42.734Z"}, "model": "auth.user", "pk": 64}, {"fields": {"username": "ugo.sangiorgi", "first_name": "Ugo", "last_name": "Sangiorgi", "is_active": true, "is_superuser": false, "is_staff": false, "last_login": "2015-11-16T03:35:30.372Z", "groups": [], "user_permissions": [], "password": "!LuSwRZkzW3riUGLwWHxPPPzMQtjMwhAWdyg4FtIu", "email": "ugo.sangiorgi@gmail.com", "date_joined": "2015-11-16T03:35:30.247Z"}, "model": "auth.user", "pk": 65}]